AUTHORS.rst
CONTRIBUTING.rst
HISTORY.rst
LICENSE
MANIFEST.in
README.rst
setup.cfg
setup.py
docs/Makefile
docs/authors.rst
docs/conf.py
docs/contributing.rst
docs/history.rst
docs/index.rst
docs/installation.rst
docs/make.bat
docs/readme.rst
docs/usage.rst
inaugurate/__init__.py
inaugurate/cli.py
inaugurate/inaugurate.py
inaugurate.egg-info/PKG-INFO
inaugurate.egg-info/SOURCES.txt
inaugurate.egg-info/dependency_links.txt
inaugurate.egg-info/entry_points.txt
inaugurate.egg-info/not-zip-safe
inaugurate.egg-info/requires.txt
inaugurate.egg-info/top_level.txt
tests/__init__.py
tests/test_inaugurate.py