Metadata-Version: 1.1
Name: inaugurate
Version: 0.1.0
Summary: hit the ground running bootstrap 
Home-page: https://github.com/makkus/inaugurate
Author: Markus Binsteiner
Author-email: makkus@posteo.de
License: GNU General Public License v3
Keywords: inaugurate
Platform: UNKNOWN
Classifier: Development Status :: 2 - Pre-Alpha
Classifier: Intended Audience :: Developers
Classifier: License :: OSI Approved :: GNU General Public License v3 (GPLv3)
Classifier: Natural Language :: English
Classifier: Programming Language :: Python :: 2
Classifier: Programming Language :: Python :: 2.6
Classifier: Programming Language :: Python :: 2.7
Classifier: Programming Language :: Python :: 3
Classifier: Programming Language :: Python :: 3.3
Classifier: Programming Language :: Python :: 3.4
Classifier: Programming Language :: Python :: 3.5
